magnopy/__init__.py
magnopy/__main__.py
magnopy/_data_validation.py
magnopy/_diagonalization.py
magnopy/_energy.py
magnopy/_exceptions.py
magnopy/_local_rf.py
magnopy/_lswt.py
magnopy/_osfix.py
magnopy/_package_info.py
magnopy/_parallelization.py
magnopy/_plotly_engine.py
magnopy/experimental.py
magnopy/_cli/__init__.py
magnopy/_cli/_arguments_library.py
magnopy/_cli/_cli_optimize_sd.py
magnopy/_cli/_cli_solve_lswt.py
magnopy/_constants/__init__.py
magnopy/_constants/_conventions.py
magnopy/_constants/_icons.py
magnopy/_constants/_si.py
magnopy/_constants/_units.py
magnopy/_parameters/__init__.py
magnopy/_parameters/_p22.py
magnopy/_parameters/_p422.py
magnopy/_spinham/__init__.py
magnopy/_spinham/_c1.py
magnopy/_spinham/_c21.py
magnopy/_spinham/_c22.py
magnopy/_spinham/_c31.py
magnopy/_spinham/_c32.py
magnopy/_spinham/_c33.py
magnopy/_spinham/_c41.py
magnopy/_spinham/_c421.py
magnopy/_spinham/_c422.py
magnopy/_spinham/_c43.py
magnopy/_spinham/_c44.py
magnopy/_spinham/_convention.py
magnopy/_spinham/_hamiltonian.py
magnopy/_spinham/_supercell.py
magnopy/examples/__init__.py
magnopy/examples/_ferro.py
magnopy/examples/_other.py
magnopy/io/__init__.py
magnopy/io/_grogu.py
magnopy/io/_k_resolved.py
magnopy/io/_png_plots.py
magnopy/io/_spin_directions.py
magnopy/io/_tb2j.py
magnopy/io/_vampire.py
magnopy/io/_warnings.py
magnopy/scenarios/__init__.py
magnopy/scenarios/_optimize_sd.py
magnopy/scenarios/_solve_lswt.py
magnopy-0.4.3.dist-info/licenses/LICENSE
magnopy-0.4.3.dist-info/METADATA
magnopy-0.4.3.dist-info/WHEEL
magnopy-0.4.3.dist-info/entry_points.txt
magnopy-0.4.3.dist-info/top_level.txt
magnopy-0.4.3.dist-info/RECORD
