Metadata-Version: 2.4
Name: magnopy
Version: 0.4.3
Summary: Magnopy is a Python package for magnons.
Author-email: Andrey Rybakov <rybakov.ad@icloud.com>
License-Expression: GPL-3.0-or-later
Project-URL: Homepage, https://magnopy.org
Project-URL: Documentation, https://magnopy.org
Project-URL: Repository, https://github.com/magnopy/magnopy.git
Project-URL: Issues, https://github.com/magnopy/magnopy/issues
Project-URL: Changelog, https://magnopy.org/en/latest/release-notes/index.html
Classifier: Development Status :: 4 - Beta
Classifier: Intended Audience :: Science/Research
Classifier: Intended Audience :: Developers
Classifier: Intended Audience :: Education
Classifier: Intended Audience :: End Users/Desktop
Classifier: Programming Language :: Python
Classifier: Programming Language :: Python :: 3
Classifier: Programming Language :: Python :: 3.9
Classifier: Programming Language :: Python :: 3.10
Classifier: Programming Language :: Python :: 3.11
Classifier: Programming Language :: Python :: 3.12
Classifier: Programming Language :: Python :: 3.13
Classifier: Programming Language :: Python :: 3.14
Classifier: Programming Language :: Python :: 3 :: Only
Classifier: Topic :: Software Development
Classifier: Topic :: Scientific/Engineering
Classifier: Operating System :: OS Independent
Requires-Python: >=3.9
License-File: LICENSE
Requires-Dist: numpy
Requires-Dist: wulfric==0.6.*,>=0.6.3
Provides-Extra: visual
Requires-Dist: matplotlib; extra == "visual"
Requires-Dist: plotly; extra == "visual"
Requires-Dist: wulfric[visual]==0.6.*,>=0.6.3; extra == "visual"
Dynamic: license-file
